README.md
setup.py
empy/__init__.py
kooki/__init__.py
kooki/exception.py
kooki/tools.py
kooki/version.py
kooki.egg-info/PKG-INFO
kooki.egg-info/SOURCES.txt
kooki.egg-info/dependency_links.txt
kooki.egg-info/entry_points.txt
kooki.egg-info/requires.txt
kooki.egg-info/top_level.txt
kooki/cli/__init__.py
kooki/cli/bake.py
kooki/cli/command.py
kooki/config/__init__.py
kooki/config/check.py
kooki/config/config.py
kooki/config/document.py
kooki/config/parse.py
kooki/processor/__init__.py
kooki/processor/common.py
kooki/processor/exception.py
kooki/processor/extension.py
kooki/processor/jars.py
kooki/processor/metadata.py
kooki/processor/process.py
kooki/processor/renderer.py
pretty_output/__init__.py
scripts/kooki