Metadata-Version: 1.1
Name: kooki
Version: 0.19.3
Summary: The ultimate document generator.
Home-page: https://gitlab.com/kooki/kooki
Author: Noel Martignoni
Author-email: noel@martignoni.fr
License: UNKNOWN
Keywords: document generator template markdown YAML
Platform: UNKNOWN
Classifier: Development Status :: 4 - Beta
Classifier: Environment :: Console
Classifier: Intended Audience :: End Users/Desktop
Classifier: Intended Audience :: Developers
Classifier: Intended Audience :: Science/Research
Classifier: Intended Audience :: System Administrators
Classifier: License :: OSI Approved :: BSD License
Classifier: Operating System :: POSIX :: Linux
Classifier: Programming Language :: Python
Classifier: Topic :: Office/Business
Classifier: Topic :: Text Processing
Classifier: Topic :: Utilities
